<?xml version="1.0" encoding="utf-8"?>

<root>
   <configField>
      <configGroupName>LightSource</configGroupName>
      <config>
         <name>LightSource</name>
         <values>
            <value>LED</value>
         </values>
      </config>
      <config>
         <name>ScintDecay</name>
         <values>
            <value>45</value>
         </values>
      </config>
      <config>
         <name>LEDWidth</name>
         <values>
            <value>50</value>
         </values>
      </config>
   </configField>
   <configField>
      <configGroupName>SiPMCharacteristics</configGroupName>
      <config>
         <name>SinglePulseWidth</name>
         <values>
            <value>20</value>
         </values>
      </config>
      <config>
         <name>AfterPulseTimeConstant</name>
         <values>
            <value>100</value>
         </values>
      </config>
      <config>
         <name>Lambda</name>
         <values>
            <value>0.06</value>
         </values>
      </config>
      <config>
         <name>Alpha</name>
         <values>
            <value>0.1</value>
         </values>
      </config>
      <config>
         <name>Gain</name>
         <values>
            <value>1</value>
         </values>
      </config>
      <config>
         <name>DarkNoiseFrequency</name>
         <values>
            <value>0</value>
         </values>
      </config>
   </configField>
   <configField>
      <configGroupName>WFAnalysis</configGroupName>
      <!-- <configs> -->
      <config>
         <name>IntStart</name>
         <values>
            <value>0</value>
         </values>
      </config>
      <config>
         <name>IntEnd</name>
         <values>
            <value>300</value>
         </values>
      </config>
      <config>
         <name>BLstart</name>
         <values>
            <value>-380</value>
         </values>
      </config>
      <config>
         <name>BLend</name>
         <values>
            <value>-20</value>
         </values>
      </config>
   </configField>
   <configField>
      <configGroupName>SimulationInput</configGroupName>
      <!-- <configs> -->
      <config>
         <name>RangeMin</name>
         <values>
            <value>1</value>
         </values>
      </config>
      <config>
         <name>RangeMax</name>
         <values>
            <value>1</value>
         </values>
      </config>
      <config>
         <name>Nstep</name>
         <values>
            <value>1</value>
         </values>
      </config>
      <config>
         <name>Ndiff</name>
         <values>
            <value>2</value>
         </values>
      </config>
      <config>
         <name>Nevent</name>
         <values>
            <value>5000</value>
         </values>
      </config>
      <config>
         <name>Nbins</name>
         <values>
            <value>1100</value>
         </values>
      </config>
      <config>
         <name>NoiseLevel</name>
         <values>
            <value>0</value>
            <value>0.005</value>
            <value>0.01</value>
            <value>0.02</value>
            <value>0.04</value>
         </values>
      </config>
      <config>
         <name>PixelNoise</name>
         <values>
            <value>0.04</value>
         </values>
      </config>
   </configField>
</root>
